setup.py
xmlbegone.py
xmlbegone.egg-info/PKG-INFO
xmlbegone.egg-info/SOURCES.txt
xmlbegone.egg-info/dependency_links.txt
xmlbegone.egg-info/requires.txt
xmlbegone.egg-info/top_level.txt