Metadata-Version: 1.0
Name: xmlbegone
Version: 0.1
Summary: xmlbegone turns reasonable XML into simple dicts.
Home-page: UNKNOWN
Author: Steven Hazel
Author-email: sah@awesame.org
License: UNKNOWN
Platform: UNKNOWN
